[{"successCallback":[{"dataType":"ActionInfoDTO Object","name":null,"isArray":true,"sample":"","subParam":[{"dataType":"String","name":"id","isArray":false,"sample":"","subParam":[]},{"dataType":"String","name":"description","isArray":false,"sample":"","subParam":[]},{"dataType":"String","name":"name","isArray":false,"sample":"","subParam":[]},{"dataType":"String","name":"serviceType","isArray":false,"sample":"","subParam":[]},{"dataType":"String","name":"instanceList","isArray":true,"sample":"","subParam":[]}]}],"javaMethodName":"getActionInfoList","method":"GET","javaClass":"com.infinities.cloudfusion.vm.ParamRestfulService","bodyParam":[],"title":"Get Action Info List","url":"/parameter/action","urlParam":[]},{"successCallback":[{"dataType":"String","name":null,"isArray":true,"sample":"","subParam":[]}],"javaMethodName":"getRuleConditionOperatorSelectList","method":"GET","javaClass":"com.infinities.cloudfusion.vm.ParamRestfulService","bodyParam":[],"title":"Get Rule Condition Operator Select List","url":"/parameter/comparisonoperator","urlParam":[]},{"successCallback":[{"dataType":"String","name":null,"isArray":true,"sample":"","subParam":[]}],"javaMethodName":"getMonitorTargetSelectList","method":"GET","javaClass":"com.infinities.cloudfusion.vm.ParamRestfulService","bodyParam":[],"title":"Get Monitor Target Select List","url":"/parameter/monitortarget","urlParam":[]},{"successCallback":[{"dataType":"String","name":null,"isArray":true,"sample":"","subParam":[]}],"javaMethodName":"getRuleOperatorSelectList","method":"GET","javaClass":"com.infinities.cloudfusion.vm.ParamRestfulService","bodyParam":[],"title":"Get Rule Operator Select List","url":"/parameter/relationoperator","urlParam":[]}]