[{"bodyParam":[{"defaultValue":null,"isArray":false,"name":null,"schema":{"type":"object","id":"urn:jsonschema:com:infinities:cloudfusion:admin:dto:UserServiceAccessInfoDTO","properties":{"userId":{"type":"string"},"accessKeyId":{"type":"string"},"accessKeySecret":{"type":"string"},"cloudProvider":{"type":"string"}}}}],"javaClass":"com.infinities.cloudfusion.admin.AccessKeyRest","javaMethodName":"add","method":"POST","successCallback":[{"defaultValue":null,"isArray":false,"name":null,"schema":{"type":"boolean"}}],"title":"Add","url":"/accesskey/","urlParam":[]},{"bodyParam":[{"defaultValue":null,"isArray":false,"name":null,"schema":{"type":"object","id":"urn:jsonschema:com:infinities:cloudfusion:admin:dto:UserServiceAccessInfoDTO","properties":{"userId":{"type":"string"},"accessKeyId":{"type":"string"},"accessKeySecret":{"type":"string"},"cloudProvider":{"type":"string"}}}}],"javaClass":"com.infinities.cloudfusion.admin.AccessKeyRest","javaMethodName":"update","method":"PUT","successCallback":[{"defaultValue":null,"isArray":false,"name":null,"schema":{"type":"boolean"}}],"title":"Update","url":"/accesskey/","urlParam":[]},{"bodyParam":[],"javaClass":"com.infinities.cloudfusion.admin.AccessKeyRest","javaMethodName":"delete","method":"DELETE","successCallback":[{"defaultValue":null,"isArray":false,"name":null,"schema":{"type":"boolean"}}],"title":"Delete","url":"/accesskey/","urlParam":[{"defaultValue":null,"isArray":false,"name":"userId","schema":{"type":"string"}},{"defaultValue":null,"isArray":false,"name":"providerId","schema":{"type":"string"}}]},{"bodyParam":[],"javaClass":"com.infinities.cloudfusion.admin.AccessKeyRest","javaMethodName":"list","method":"GET","successCallback":[{"defaultValue":null,"isArray":true,"name":null,"schema":{"type":"object","id":"urn:jsonschema:com:infinities:cloudfusion:admin:dto:UserServiceAccessInfoDTO","properties":{"userId":{"type":"string"},"accessKeyId":{"type":"string"},"accessKeySecret":{"type":"string"},"cloudProvider":{"type":"string"}}}}],"title":"List","url":"/accesskey/list/{companyId}","urlParam":[{"defaultValue":null,"isArray":false,"name":"{companyId}","schema":{"type":"string"}}]},{"bodyParam":[],"javaClass":"com.infinities.cloudfusion.admin.AccessKeyRest","javaMethodName":"companyTree","method":"GET","successCallback":[{"defaultValue":null,"isArray":false,"name":null,"schema":{"type":"object","additionalProperties":{"type":"any"}}}],"title":"Company Tree","url":"/accesskey/map1/{companyId}","urlParam":[{"defaultValue":null,"isArray":false,"name":"{companyId}","schema":{"type":"string"}}]},{"bodyParam":[],"javaClass":"com.infinities.cloudfusion.admin.AccessKeyRest","javaMethodName":"map2","method":"GET","successCallback":[{"defaultValue":null,"isArray":false,"name":null,"schema":{"type":"object","additionalProperties":{"type":"any"}}}],"title":"Map 2","url":"/accesskey/map2/{companyId}","urlParam":[{"defaultValue":null,"isArray":false,"name":"{companyId}","schema":{"type":"string"}}]}]