[{"bodyParam":[],"javaClass":"com.infinities.cloudfusion.rest.admin.AdminDashboardRest","javaMethodName":"getAdminDashboard","method":"GET","successCallback":[{"defaultValue":null,"isArray":false,"name":null,"schema":{"type":"object","id":"urn:jsonschema:com:infinities:cloudfusion:admin:dto:DashboardParameters","properties":{"activeSessionCount":{"type":"integer"},"activeErrorHandlingTaskCount":{"type":"integer"},"onProccessErrorHandlingTaskCount":{"type":"integer"},"todaysOrderCount":{"type":"integer"},"todaysRegistedUserCount":{"type":"integer"},"activeProjectCount":{"type":"integer"},"manageServicesCount":{"type":"object","additionalProperties":{"type":"integer"}}}}}],"title":"Get Admin Dashboard","url":"/dashboard/admin/parameters","urlParam":[{"defaultValue":null,"isArray":false,"name":"data","schema":{"type":"string"}},{"defaultValue":null,"isArray":false,"name":"period","schema":{"type":"string"}}]},{"bodyParam":[],"javaClass":"com.infinities.cloudfusion.rest.admin.AdminDashboardRest","javaMethodName":"getAdminDashboard","method":"GET","successCallback":[],"title":"Get Admin Dashboard","url":"/dashboard/admin/{cloudproviderId}","urlParam":[{"defaultValue":null,"isArray":false,"name":"{cloudproviderId}","schema":{"type":"string"}},{"defaultValue":null,"isArray":false,"name":"data","schema":{"type":"string"}},{"defaultValue":null,"isArray":false,"name":"period","schema":{"type":"string"}}]}]