[{"bodyParam":[{"defaultValue":null,"isArray":false,"name":null,"schema":{"type":"object","additionalProperties":{"type":"any"}}}],"javaClass":"com.infinities.cloudfusion.um.UserMailRest","javaMethodName":"doInsert","method":"POST","successCallback":[{"defaultValue":null,"isArray":false,"name":null,"schema":{"type":"object","additionalProperties":{"type":"any"}}}],"title":"Do Insert","url":"/usermail/","urlParam":[]},{"bodyParam":[],"javaClass":"com.infinities.cloudfusion.um.UserMailRest","javaMethodName":"doDelete","method":"DELETE","successCallback":[{"defaultValue":null,"isArray":false,"name":null,"schema":{"type":"boolean"}}],"title":"Do Delete","url":"/usermail/","urlParam":[{"defaultValue":null,"isArray":false,"name":"id","schema":{"type":"string"}}]},{"bodyParam":[{"defaultValue":null,"isArray":false,"name":null,"schema":{"type":"object","additionalProperties":{"type":"any"}}}],"javaClass":"com.infinities.cloudfusion.um.UserMailRest","javaMethodName":"doNotifyIO","method":"POST","successCallback":[{"defaultValue":null,"isArray":false,"name":null,"schema":{"type":"boolean"}}],"title":"Do Notify IO","url":"/usermail/notifyio","urlParam":[]},{"bodyParam":[{"defaultValue":null,"isArray":false,"name":null,"schema":{"type":"object","additionalProperties":{"type":"any"}}}],"javaClass":"com.infinities.cloudfusion.um.UserMailRest","javaMethodName":"doSendVerify","method":"POST","successCallback":[{"defaultValue":null,"isArray":false,"name":null,"schema":{"type":"boolean"}}],"title":"Do Send Verify","url":"/usermail/sendverify","urlParam":[]}]